chromaquant/__init__.py
chromaquant/__main__.py
chromaquant/oldui.py
chromaquant/properties.json
chromaquant/Handle/__init__.py
chromaquant/Handle/fileChecks.py
chromaquant/Handle/handleDirectories.py
chromaquant/Hydro/__init__.py
chromaquant/Hydro/hydroMain.py
chromaquant/Manual/HydroUI.py
chromaquant/Manual/QuantUPP.py
chromaquant/Manual/Quantification.py
chromaquant/Manual/__init__.py
chromaquant/Manual/duplicateMatch.py
chromaquant/Manual/fpm_match.py
chromaquant/Manual/label-type.py
chromaquant/Match/AutoFpmMatch.py
chromaquant/Match/__init__.py
chromaquant/Match/matchMain.py
chromaquant/Match/MatchSub/__init__.py
chromaquant/Match/MatchSub/matchTools.py
chromaquant/Match/MatchSub/peakTools.py
chromaquant/Quant/AutoQuantification.py
chromaquant/Quant/__init__.py
chromaquant/Quant/quantMain.py
chromaquant/Quant/QuantSub/__init__.py
chromaquant/Quant/QuantSub/gasFID.py
chromaquant/Quant/QuantSub/gasTCD.py
chromaquant/Quant/QuantSub/liquidFID.py
chromaquant/Quant/QuantSub/parseTools.py
chromaquant/UAPP/__init__.py
chromaquant/UAPP/uappMain.py
chromaquant-0.4.0.dist-info/METADATA
chromaquant-0.4.0.dist-info/WHEEL
chromaquant-0.4.0.dist-info/entry_points.txt
chromaquant-0.4.0.dist-info/licenses/LICENSE.txt
chromaquant-0.4.0.dist-info/licenses/LICENSES_bundled.txt
chromaquant-0.4.0.dist-info/RECORD
