Metadata-Version: 2.4
Name: chromaquant
Version: 0.4.0
Summary: Analytical platform for gas chromatography
Project-URL: Repository, https://github.com/JnliaH/ChromaQuant
Author: Julia Hancock
License: 
License-File: LICENSE.txt
License-File: LICENSES_bundled.txt
Keywords: Analysis,Analytical Chemistry,Chromatography,Complex Hydrocarbon Analysis,Mass Spectrometry
Classifier: Development Status :: 2 - Pre-Alpha
Classifier: Environment :: MacOS X
Classifier: License :: OSI Approved :: BSD License
Classifier: Natural Language :: English
Classifier: Programming Language :: Python :: 3
Classifier: Topic :: Scientific/Engineering :: Chemistry
Requires-Python: >=3.12
Requires-Dist: chemformula~=1.3.1
Requires-Dist: molmass~=2024.5.24
Requires-Dist: numpy~=1.26.4
Requires-Dist: openpyxl~=3.1.5
Requires-Dist: pandas~=2.2.2
Requires-Dist: pillow~=10.3.0
Requires-Dist: plotly~=5.22.0
Requires-Dist: pubchempy~=1.0.4
Requires-Dist: rdkit~=2024.3.5
Requires-Dist: scipy~=1.13.1
Requires-Dist: ttkthemes~=3.2.2
Requires-Dist: xlsxwriter~=3.2.0
